dubbo/__init__.py
dubbo/client.py
dubbo/codec/__init__.py
dubbo/codec/decoder.py
dubbo/codec/encoder.py
dubbo/common/__init__.py
dubbo/common/constants.py
dubbo/common/exceptions.py
dubbo/common/loggers.py
dubbo/common/util.py
dubbo/connection/__init__.py
dubbo/connection/connections.py
python_dubbo_support_python3-0.0.2.dist-info/LICENSE
python_dubbo_support_python3-0.0.2.dist-info/METADATA
python_dubbo_support_python3-0.0.2.dist-info/WHEEL
python_dubbo_support_python3-0.0.2.dist-info/top_level.txt
python_dubbo_support_python3-0.0.2.dist-info/RECORD
